livekit/plugins/lmnt/__init__.py
livekit/plugins/lmnt/models.py
livekit/plugins/lmnt/py.typed
livekit/plugins/lmnt/tts.py
livekit/plugins/lmnt/version.py
livekit_plugins_lmnt-1.3.11.dist-info/METADATA
livekit_plugins_lmnt-1.3.11.dist-info/WHEEL
livekit_plugins_lmnt-1.3.11.dist-info/RECORD
